universal_printer/__init__.py
universal_printer/cli.py
universal_printer/config.py
universal_printer/document_printer.py
universal_printer/exceptions.py
universal_printer/utils.py
universal_printer-3.0.0.dist-info/licenses/LICENSE
universal_printer-3.0.0.dist-info/METADATA
universal_printer-3.0.0.dist-info/WHEEL
universal_printer-3.0.0.dist-info/entry_points.txt
universal_printer-3.0.0.dist-info/top_level.txt
universal_printer-3.0.0.dist-info/RECORD
