Metadata-Version: 2.4
Name: universal-printer
Version: 3.0.0
Summary: Cross-platform document printing with enhanced PDF generation
Home-page: https://github.com/sharathkumardaroor/universal-printer
Author: Sharath Kumar Daroor
Author-email: Sharath Kumar Daroor <sharathkumardaroor@gmail.com>
Maintainer-email: Sharath Kumar Daroor <sharathkumardaroor@gmail.com>
License: MIT
Project-URL: Homepage, https://github.com/sharathkumardaroor/universal-printer
Project-URL: Documentation, https://github.com/sharathkumardaroor/universal-printer/blob/main/README.md
Project-URL: Repository, https://github.com/sharathkumardaroor/universal-printer.git
Project-URL: Bug Reports, https://github.com/sharathkumardaroor/universal-printer/issues
Project-URL: Changelog, https://github.com/sharathkumardaroor/universal-printer/blob/main/CHANGELOG.md
Keywords: printing,pdf,cross-platform,document,markdown,csv,json,text,fallback,universal,printer,windows,linux,macos,batch,conversion
Platform: any
Classifier: Development Status :: 5 - Production/Stable
Classifier: Intended Audience :: Developers
Classifier: Intended Audience :: End Users/Desktop
Classifier: License :: OSI Approved :: MIT License
Classifier: Operating System :: OS Independent
Classifier: Operating System :: Microsoft :: Windows
Classifier: Operating System :: POSIX :: Linux
Classifier: Operating System :: MacOS
Classifier: Programming Language :: Python :: 3
Classifier: Programming Language :: Python :: 3.7
Classifier: Programming Language :: Python :: 3.8
Classifier: Programming Language :: Python :: 3.9
Classifier: Programming Language :: Python :: 3.10
Classifier: Programming Language :: Python :: 3.11
Classifier: Programming Language :: Python :: 3.12
Classifier: Topic :: Printing
Classifier: Topic :: Office/Business
Classifier: Topic :: Software Development :: Libraries :: Python Modules
Classifier: Topic :: System :: Systems Administration
Classifier: Topic :: Text Processing :: General
Classifier: Topic :: Utilities
Requires-Python: >=3.7
License-File: LICENSE
Provides-Extra: dev
Requires-Dist: pytest>=6.0; extra == "dev"
Requires-Dist: pytest-cov>=2.0; extra == "dev"
Requires-Dist: black>=21.0; extra == "dev"
Requires-Dist: flake8>=3.8; extra == "dev"
Requires-Dist: mypy>=0.800; extra == "dev"
Requires-Dist: twine>=3.0; extra == "dev"
Requires-Dist: build>=0.7; extra == "dev"
Provides-Extra: test
Requires-Dist: pytest>=6.0; extra == "test"
Requires-Dist: pytest-cov>=2.0; extra == "test"
Dynamic: author
Dynamic: home-page
Dynamic: license-file
Dynamic: platform
Dynamic: requires-python
